Metadata-Version: 2.1
Name: ROSHANDELIVERY
Version: 0.0.1
Summary: DELIVERY FEE CALCULATOR
Home-page: 
Author: Roshan Singh
Author-email: roshsingh07@gmail.com
License: MIT
Keywords: calculator
Classifier: Development Status :: 5 - Production/Stable
Classifier: Intended Audience :: Education
Classifier: Operating System :: Microsoft :: Windows :: Windows 10
Classifier: License :: OSI Approved :: MIT License
Classifier: Programming Language :: Python :: 3.8
License-File: LICENCE.txt
